README.md
setup.py
tebot/__init__.py
tebot/bot.py
tebot.egg-info/PKG-INFO
tebot.egg-info/SOURCES.txt
tebot.egg-info/dependency_links.txt
tebot.egg-info/requires.txt
tebot.egg-info/top_level.txt