Metadata-Version: 2.1
Name: tebot
Version: 0.2.3
Summary: Telegram bot library for Python and humans
Home-page: https://github.com/alttch/tebot
Author: Altertech
Author-email: div@altertech.com
License: MIT
Platform: UNKNOWN
Classifier: Programming Language :: Python :: 3
Classifier: License :: OSI Approved :: MIT License
Classifier: Topic :: Software Development :: Libraries
